thinkup_cli/__init__.py
thinkup_cli/main.py
thinkup_cli/entities/__init__.py
thinkup_cli/entities/app.py
thinkup_cli/entities/menu.py
thinkup_cli/entities/setting.py
thinkup_cli/form/__init__.py
thinkup_cli/form/_form_confirm.py
thinkup_cli/form/code_gen/__init__.py
thinkup_cli/form/code_gen/code_gen_form.py
thinkup_cli/form/code_gen/create_new_module.py
thinkup_cli/form/code_gen/create_new_screen.py
thinkup_cli/form/text_review/__init__.py
thinkup_cli/form/text_review/get_from_remote_config.py
thinkup_cli/form/text_review/local_strings_template.py
thinkup_cli/form/text_review/review_figma.py
thinkup_cli/form/text_review/text_review_form.py
thinkup_cli/form/text_review/update_remote_config.py
thinkup_cli/utils/__init__.py
thinkup_cli/utils/configs.py
thinkup_cli/utils/file.py
thinkup_cli/utils/firebase.py
thinkup_cli/utils/shell.py
thinkup_cli/utils/singleton.py
thinkup_cli/utils/ui.py
thinkup_cli/utils/ui_menu.py
thinkup_cli/utils/code_templates/__init__.py
thinkup_cli/utils/code_templates/module/__init__.py
thinkup_cli/utils/code_templates/module/build_gradle_template.py
thinkup_cli/utils/code_templates/module/consumer_rules_pro_template.py
thinkup_cli/utils/code_templates/module/git_ignore_tempate.py
thinkup_cli/utils/code_templates/module/manifest_template.py
thinkup_cli/utils/code_templates/module/proguard_rules_pro_template.py
thinkup_cli/utils/code_templates/module/update_app_gradle.py
thinkup_cli/utils/code_templates/module/update_settings_gradle.py
thinkup_cli/utils/code_templates/screen/__init__.py
thinkup_cli/utils/code_templates/screen/navigation_template.py
thinkup_cli/utils/code_templates/screen/screen_template.py
thinkup_cli/utils/code_templates/screen/viewmodel_template.py
thinkup_cli-1.1.6.dist-info/METADATA
thinkup_cli-1.1.6.dist-info/WHEEL
thinkup_cli-1.1.6.dist-info/entry_points.txt
thinkup_cli-1.1.6.dist-info/top_level.txt
thinkup_cli-1.1.6.dist-info/RECORD
